zhaohua/__init__.py
zhaohua/about_time.py
zhaohua/dir.py
zhaohua/excel.py
zhaohua/for_time.py
zhaohua/ppt.py
zhaohua/rand.py
zhaohua/word.py
zhaohua-1.0.5.dist-info/METADATA
zhaohua-1.0.5.dist-info/WHEEL
zhaohua-1.0.5.dist-info/top_level.txt
zhaohua-1.0.5.dist-info/RECORD
