Metadata-Version: 2.1
Name: zhaohua
Version: 1.0.5
Summary: 一个简单的，自用的Python库。
Home-page: https://github.com/yourusername/mylibrary
Author: Zhao Hua
Author-email: zhaohua@126.com
Requires-Dist: openpyxl
Requires-Dist: pandas
Requires-Dist: numpy
Requires-Dist: requests
Requires-Dist: selenium
Requires-Dist: websocket-client
Requires-Dist: webdriver-manager
Requires-Dist: pillow
Requires-Dist: pytesseract
Requires-Dist: pdf2image
Requires-Dist: chardet
Requires-Dist: baidu-aip
